devtools_json_formatter/__init__.py
devtools_json_formatter-1.0.1.dist-info/METADATA
devtools_json_formatter-1.0.1.dist-info/WHEEL
devtools_json_formatter-1.0.1.dist-info/top_level.txt
devtools_json_formatter-1.0.1.dist-info/RECORD
